config/__init__.py
config/config.py
config/network_config.py
config/optimizer_config.py
network/__init__.py
network/activation.py
network/activation_functions.py
network/dense.py
network/layer.py
network/loss.py
network/mse.py
network/network.py
network/softmax.py
optimization/__init__.py
optimization/grid_optimizer.py
optimization/optimization_tools.py
optimization/optimizer.py
optimization/random_optimizer.py
pynetworklib-1.0.0.dist-info/METADATA
pynetworklib-1.0.0.dist-info/WHEEL
pynetworklib-1.0.0.dist-info/top_level.txt
pynetworklib-1.0.0.dist-info/RECORD
