Metadata-Version: 2.1
Name: pynetworklib
Version: 1.0.0
Summary: A simple library for makeing dense multilayer neural networks
Author: Joseph Bronsten
Author-email: josephbronsten.dev_contact@gmail.com
Requires-Dist: numpy
